setup.py
pyramid_msgpack/__init__.py
pyramid_msgpack.egg-info/PKG-INFO
pyramid_msgpack.egg-info/SOURCES.txt
pyramid_msgpack.egg-info/dependency_links.txt
pyramid_msgpack.egg-info/requires.txt
pyramid_msgpack.egg-info/top_level.txt