Metadata-Version: 1.1
Name: pyramid-msgpack
Version: 1.0.0
Summary: Pyramid view renderer to output in msgpack (as opposed to JSON).
Home-page: https://github.com/ixmatus/pyramid_msgpack
Author: Parnell Springmeyer
Author-email: parnell@ixmat.us
License: UNKNOWN
Download-URL: https://github.com/ixmatus/pyramid_msgpack
Platform: UNKNOWN
